{
  "name": "book.fantazia.entry.expendables.vitality_fruit.name",
  "icon": "fantazia:vitality_fruit",
  "category": "fantazia:expendables",
  "advancement" : "fantazia:the_worldliness/expendables/vitality_fruit",
  "pages": [
    {
      "type": "patchouli:text",
      "text": "book.fantazia.entry.expendables.vitality_fruit.page.1"
    },
    {
      "type": "spotlight",
      "item" : "fantazia:vitality_fruit",
      "text" : "book.fantazia.entry.expendables.vitality_fruit.page.2"
    }
  ]
}